gecosistema_database/__init__.py
gecosistema_database/abstractdb.py
gecosistema_database/aggregates.py
gecosistema_database/functions.py
gecosistema_database/http.py
gecosistema_database/mssqldb.py
gecosistema_database/sql_utils.py
gecosistema_database/sqlitedb.py
gecosistema_database-0.0.152.dist-info/LICENSE
gecosistema_database-0.0.152.dist-info/METADATA
gecosistema_database-0.0.152.dist-info/WHEEL
gecosistema_database-0.0.152.dist-info/top_level.txt
gecosistema_database-0.0.152.dist-info/RECORD
