Metadata-Version: 2.1
Name: gecosistema-database
Version: 0.0.152
Summary: A small example package
Home-page: https://github.com/valluzzi/gecosistema_database.git
Author: Valerio Luzzi
Author-email: valluzzi@gmail.com
License: UNKNOWN
Platform: UNKNOWN
Classifier: Programming Language :: Python :: 2
Classifier: License :: OSI Approved :: MIT License
Classifier: Operating System :: OS Independent
Requires-Dist: gecosistema-core
Requires-Dist: unicodecsv
Requires-Dist: pyodbc
Requires-Dist: numpy
Requires-Dist: scipy
